{
	"pagination": {},
	"data": [
		{
			"id": 1,
			"avatar": "/img/tmp/user-1.jpg",
			"name": "Robert L. Kidney",
			"address": "2917 Goldie Lane\nCincinnati, OH 45236",
			"company": "Shoe Kicks",
			"profile_size": 82,
			"profile_description": "Finish education content"
		},
		{
			"id": 2,
			"avatar": "/img/tmp/user-2.jpg",
			"name": "David H. Cherry",
			"address": "862 Frum Street\nNashville, TN 37212",
			"company": "Childrens Bargain Town",
			"profile_size": 50,
			"profile_description": "Contact as soon as possible"			
		},
		{
			"id": 3,
			"avatar": "/img/tmp/user-3.jpg",
			"name": "Nathanael J. Barrett",
			"address": "3373 Parrill Court\nLaporte, IN 46350",
			"company": "Castro Convertibles",
			"profile_size": 95,
			"profile_description": "No further actions required"	
		},
		{
			"id": 4,
			"avatar": "/img/tmp/user-4.jpg",
			"name": "Russell S. Davila",
			"address": "4893 Diamond Cove\nProvidence, RI 02903",
			"company": "Mars Music",
			"profile_size": 72,
			"profile_description": "Ping via via e-mail"			
		},
		{
			"id": 5,
			"avatar": "/img/tmp/user-5.jpg",
			"name": "Dennis R. Jones",
			"address": "1192 Evergreen Lane\nLos Angeles, CA 90018",
			"company": "Realty Depot",
			"profile_size": 80,
			"profile_description": "Check for PDF invoice"				
		},
		{
			"id": 6,
			"avatar": "/img/tmp/user-6.jpg",
			"name": "Janis J. Snyder",
			"address": "2739 Progress Way\nWaterloo, IA 50703",
			"company": "Gold Management",
			"profile_size": 64,
			"profile_description": "Start business conversations"				
		},
		{
			"id": 7,
			"avatar": "/img/tmp/user-7.jpg",
			"name": "Jerrold S. Kramer",
			"address": "3024 Brooke Street\nHouston, TX 77002",
			"company": "Lechmere",
			"profile_size": 90,
			"profile_description": "Send satisfaction survey"				
		},
		{
			"id": 8,
			"avatar": "/img/tmp/user-8.jpg",
			"name": "Lindsay R. Carpenter",
			"address": "1925 Dark Hollow Road\nMaple Shade, NJ 08052",
			"company": "The Flying Bear",
			"profile_size": 95,
			"profile_description": "No further actions required"				
		},
		{
			"id": 9,
			"avatar": "/img/tmp/user-9.jpg",
			"name": "Moses A. Hurst",
			"address": "3383 Clay Lick Road\nLongmont, CO 80501",
			"company": "Omni Superstore",
			"profile_size": 72,
			"profile_description": "Contact as soon as possible"				
		},
		{
			"id": 10,
			"avatar": "/img/tmp/user-10.jpg",
			"name": "Albert L. Jackson",
			"address": "2364 Marie Street\nBaltimore, MD 21231",
			"company": "Rickel",
			"profile_size": 89,
			"profile_description": "Finish education content"				
		}
	]
}
